diao/__init__.py
diao/__main__.py
diao/app.py
diao/audiotools/__init__.py
diao/audiotools/post.py
diao/audiotools/preference.py
diao/audiotools/core/__init__.py
diao/audiotools/core/audio_signal.py
diao/audiotools/core/display.py
diao/audiotools/core/dsp.py
diao/audiotools/core/effects.py
diao/audiotools/core/ffmpeg.py
diao/audiotools/core/loudness.py
diao/audiotools/core/playback.py
diao/audiotools/core/util.py
diao/audiotools/core/whisper.py
diao/audiotools/core/templates/__init__.py
diao/audiotools/core/templates/headers.html
diao/audiotools/core/templates/pandoc.css
diao/audiotools/core/templates/widget.html
diao/audiotools/data/__init__.py
diao/audiotools/data/datasets.py
diao/audiotools/data/preprocess.py
diao/audiotools/data/transforms.py
diao/audiotools/metrics/__init__.py
diao/audiotools/metrics/distance.py
diao/audiotools/metrics/quality.py
diao/audiotools/metrics/spectral.py
diao/audiotools/ml/__init__.py
diao/audiotools/ml/accelerator.py
diao/audiotools/ml/decorators.py
diao/audiotools/ml/experiment.py
diao/audiotools/ml/layers/__init__.py
diao/audiotools/ml/layers/base.py
diao/audiotools/ml/layers/spectral_gate.py
diao/dac/__init__.py
diao/dac/__main__.py
diao/dac/compare/__init__.py
diao/dac/compare/encodec.py
diao/dac/model/__init__.py
diao/dac/model/base.py
diao/dac/model/dac.py
diao/dac/model/discriminator.py
diao/dac/nn/__init__.py
diao/dac/nn/layers.py
diao/dac/nn/loss.py
diao/dac/nn/quantize.py
diao/dac/utils/__init__.py
diao/dac/utils/decode.py
diao/dac/utils/encode.py
diao/dia/__init__.py
diao/dia/audio.py
diao/dia/config.py
diao/dia/layers.py
diao/dia/model.py
diao/dia/state.py
diao-0.0.5.dist-info/LICENSE
diao-0.0.5.dist-info/WHEEL
diao-0.0.5.dist-info/METADATA
diao-0.0.5.dist-info/RECORD
