Metadata-Version: 2.1
Name: diao
Version: 0.0.5
Summary: text-to-speech synthesis
Author-email: calcuis <info@calcu.io>
Classifier: License :: OSI Approved :: MIT License
Requires-Dist: torchaudio
Requires-Dist: julius
Requires-Dist: soundfile
Requires-Dist: flatten_dict
Requires-Dist: argbind
Project-URL: GitHub, https://github.com/calcuis/text-to-speech-synthesis
Project-URL: Issues, https://github.com/calcuis/text-to-speech-synthesis/issues
